{
  "swagger": "2.0",
  "info": {
    "title": "Retrieval API",
    "version": "version not set"
  },
  "tags": [
    {
      "name": "RetrievalAPI"
    }
  ],
  "consumes": [
    "application/json"
  ],
  "produces": [
    "application/json"
  ],
  "paths": {
    "/v1/check/GetAllAdvisors": {
      "post": {
        "summary": "Get all advisors",
        "description": "Retrieves all advisors a user is entitled to according to the tier.",
        "operationId": "RetrievalAPI_GetAllAdvisors",
        "responses": {
          "200": {
            "description": "A successful response.",
            "schema": {
              "$ref": "#/definitions/v1GetAllAdvisorsResponse"
            }
          },
          "default": {
            "description": "An unexpected error response.",
            "schema": {
              "$ref": "#/definitions/rpcStatus"
            }
          }
        },
        "parameters": [
          {
            "name": "body",
            "in": "body",
            "required": true,
            "schema": {
              "$ref": "#/definitions/v1GetAllAdvisorsRequest"
            }
          }
        ],
        "tags": [
          "RetrievalAPI"
        ],
        "consumes": [
          "application/json"
        ],
        "produces": [
          "application/json"
        ]
      }
    },
    "/v1/check/GetAllAlertRuleTemplates": {
      "post": {
        "summary": "Get all alert rule templates",
        "description": "Retrieves all alert rule templates a user is entitled to according to the tier.",
        "operationId": "RetrievalAPI_GetAllAlertRuleTemplates",
        "responses": {
          "200": {
            "description": "A successful response.",
            "schema": {
              "$ref": "#/definitions/v1GetAllAlertRuleTemplatesResponse"
            }
          },
          "default": {
            "description": "An unexpected error response.",
            "schema": {
              "$ref": "#/definitions/rpcStatus"
            }
          }
        },
        "parameters": [
          {
            "name": "body",
            "in": "body",
            "required": true,
            "schema": {
              "$ref": "#/definitions/v1GetAllAlertRuleTemplatesRequest"
            }
          }
        ],
        "tags": [
          "RetrievalAPI"
        ],
        "consumes": [
          "application/json"
        ],
        "produces": [
          "application/json"
        ]
      }
    },
    "/v1/check/GetAllChecks": {
      "post": {
        "summary": "Get all checks",
        "description": "Retrieves all check scripts a user is entitled to according to the tier.",
        "operationId": "RetrievalAPI_GetAllChecks",
        "responses": {
          "200": {
            "description": "A successful response.",
            "schema": {
              "$ref": "#/definitions/v1GetAllChecksResponse"
            }
          },
          "default": {
            "description": "An unexpected error response.",
            "schema": {
              "$ref": "#/definitions/rpcStatus"
            }
          }
        },
        "parameters": [
          {
            "name": "body",
            "in": "body",
            "required": true,
            "schema": {
              "$ref": "#/definitions/v1GetAllChecksRequest"
            }
          }
        ],
        "tags": [
          "RetrievalAPI"
        ],
        "consumes": [
          "application/json"
        ],
        "produces": [
          "application/json"
        ]
      }
    },
    "/v1/check/checks": {
      "post": {
        "summary": "Updates the check results.",
        "description": "Accepts the information about the check runs and stores it into DB. The newer check replaces the older one.",
        "operationId": "RetrievalAPI_UpdateAdvisorsStatus",
        "responses": {
          "200": {
            "description": "A successful response.",
            "schema": {
              "$ref": "#/definitions/v1UpdateAdvisorsStatusResponse"
            }
          },
          "default": {
            "description": "An unexpected error response.",
            "schema": {
              "$ref": "#/definitions/rpcStatus"
            }
          }
        },
        "parameters": [
          {
            "name": "body",
            "in": "body",
            "required": true,
            "schema": {
              "$ref": "#/definitions/v1UpdateAdvisorsStatusRequest"
            }
          }
        ],
        "tags": [
          "RetrievalAPI"
        ],
        "consumes": [
          "application/json"
        ],
        "produces": [
          "application/json"
        ]
      }
    }
  },
  "definitions": {
    "protobufAny": {
      "type": "object",
      "properties": {
        "@type": {
          "type": "string"
        }
      },
      "additionalProperties": {}
    },
    "rpcStatus": {
      "type": "object",
      "properties": {
        "code": {
          "type": "integer",
          "format": "int32"
        },
        "message": {
          "type": "string"
        },
        "details": {
          "type": "array",
          "items": {
            "$ref": "#/definitions/protobufAny"
          }
        }
      }
    },
    "v1Check": {
      "type": "object",
      "properties": {
        "pmmServerId": {
          "type": "string",
          "description": "PMMServerID of the PMM that sends the request."
        },
        "serviceName": {
          "type": "string",
          "description": "name of the service that was checked."
        },
        "advisor": {
          "type": "string",
          "description": "name of the advisor that the check belongs to."
        },
        "name": {
          "type": "string",
          "title": "name of the executed check"
        },
        "version": {
          "type": "string",
          "title": "version of the executed check"
        },
        "family": {
          "type": "string",
          "title": "family of the executed check"
        },
        "category": {
          "type": "string",
          "title": "category of the executed check"
        },
        "success": {
          "type": "boolean",
          "title": "result of the executed check"
        },
        "executedAt": {
          "type": "string",
          "format": "date-time",
          "title": "time the check was executed"
        }
      }
    },
    "v1GetAllAdvisorsRequest": {
      "type": "object"
    },
    "v1GetAllAdvisorsResponse": {
      "type": "object",
      "properties": {
        "file": {
          "type": "string",
          "description": "List of advisors in YAML format."
        },
        "signatures": {
          "type": "array",
          "items": {
            "type": "string"
          },
          "description": "File signatures."
        }
      }
    },
    "v1GetAllAlertRuleTemplatesRequest": {
      "type": "object"
    },
    "v1GetAllAlertRuleTemplatesResponse": {
      "type": "object",
      "properties": {
        "file": {
          "type": "string",
          "description": "List of alert rule templates in YAML format."
        },
        "signatures": {
          "type": "array",
          "items": {
            "type": "string"
          },
          "description": "File signatures."
        }
      }
    },
    "v1GetAllChecksRequest": {
      "type": "object"
    },
    "v1GetAllChecksResponse": {
      "type": "object",
      "properties": {
        "file": {
          "type": "string",
          "description": "List of advisor checks in YAML format."
        },
        "signatures": {
          "type": "array",
          "items": {
            "type": "string"
          },
          "description": "File signatures."
        }
      }
    },
    "v1UpdateAdvisorsStatusRequest": {
      "type": "object",
      "properties": {
        "checks": {
          "type": "array",
          "items": {
            "$ref": "#/definitions/v1Check"
          }
        }
      }
    },
    "v1UpdateAdvisorsStatusResponse": {
      "type": "object"
    }
  },
  "x-readme": {
    "samples-languages": [
      "curl",
      "go",
      "node",
      "python"
    ]
  }
}
